{
    "ports": {
        "2048.zip": 39359,
        "a7xpg.zip": 2053,
        "abbayedesmorts.zip": 1049,
        "abes_adventure.zip": 7416,
        "abombniball.zip": 1587,
        "absolutereflex.zip": 1245,
        "abuse.zip": 12698,
        "afternoonstalker.zip": 247,
        "air.zip": 602,
        "akeyspath.zip": 956,
        "alchemyquest.zip": 2100,
        "alephone-marathon.zip": 10267,
        "alephone-marathon2.zip": 6554,
        "alephone-marathoninfinity.zip": 6366,
        "alienblaster.zip": 2504,
        "alienpogs.zip": 257,
        "aliensquatter.zip": 1017,
        "am2r.zip": 23391,
        "anarch.zip": 3232,
        "angband.zip": 1626,
        "annalynn.zip": 499,
        "anodyne.zip": 2919,
        "apocrunner.zip": 1706,
        "apotris.zip": 18562,
        "apricots.zip": 1662,
        "arengius.zip": 109,
        "arkovstower.zip": 1543,
        "armagetronad.zip": 1441,
        "assaultshell.zip": 159,
        "asylum.zip": 639,
        "augustus.zip": 3136,
        "avp.zip": 8212,
        "axecop.zip": 180,
        "axiom.verge.zip": 12655,
        "balatro.zip": 20983,
        "banana.duck.zip": 5241,
        "bananaguy2.zip": 2999,
        "bananaguyclassic.zip": 1878,
        "barbarian.zip": 1277,
        "battalion.zip": 379,
        "bbja.zip": 3508,
        "beat2x.zip": 5860,
        "beemisthecurseofgod.zip": 122,
        "belleboomerang.zip": 254,
        "benboquest.zip": 772,
        "bermuda_syndrome.zip": 3803,
        "billyfrontier.zip": 2293,
        "binarystarinfinity.zip": 57,
        "biolab.zip": 845,
        "biomassgrowth.zip": 657,
        "bitsybox.zip": 360,
        "bittriprunner2.zip": 2154,
        "blackout.zip": 181,
        "blastius.zip": 1368,
        "bleed.zip": 3560,
        "bleed2.zip": 3800,
        "blobby.volley2.zip": 5621,
        "bloboats.zip": 190,
        "blobwars.zip": 2649,
        "block.attack.zip": 3546,
        "blockdude_playdate.zip": 1057,
        "blockout2.zip": 4012,
        "blood.zip": 10530,
        "blossomtales2.zip": 2710,
        "bluerevolver.zip": 1157,
        "blues.brothers.zip": 4991,
        "bnbmax.zip": 1139,
        "bnbtourn.zip": 929,
        "boneraiserminions.zip": 685,
        "boni.zip": 664,
        "bootlegbox.zip": 1164,
        "boswars.zip": 819,
        "botbreak.zip": 2539,
        "botvice.zip": 2675,
        "bowlingcross.zip": 3253,
        "boxspace.zip": 52,
        "bravedogsroad.zip": 866,
        "breaker.zip": 506,
        "brittleblade.zip": 155,
        "brogue.zip": 2054,
        "brokenpipes.zip": 96,
        "bstone-aog.zip": 6551,
        "bstone-ps.zip": 2904,
        "bugdom.zip": 1048,
        "bugscraper.zip": 1531,
        "bumpersbroadswords.zip": 1821,
        "bunnysflowers.zip": 406,
        "burgerspace.zip": 335,
        "burst.zip": 1029,
        "bytepath.zip": 1846,
        "bzflag.zip": 1143,
        "c-dogs.zip": 4561,
        "candybag.zip": 61,
        "cannonball-lr.zip": 5999,
        "cannonball-st.zip": 5235,
        "cannonball.zip": 3563,
        "cardswithpersonalities.zip": 813,
        "carmageddon.zip": 6548,
        "carriesorderup.zip": 495,
        "cataclysm-dda.zip": 2252,
        "catacomb.zip": 135,
        "catacomb3d.zip": 98,
        "catacomb89.zip": 144,
        "catsonmars.zip": 284,
        "cattactics.zip": 1778,
        "catwarrior.zip": 158,
        "cave.story-evo.zip": 20640,
        "cave.story.zip": 13774,
        "cavebuster.zip": 2379,
        "cavecrawler.zip": 1144,
        "caveexpress.zip": 1599,
        "cavepacker.zip": 861,
        "cceleste.zip": 22950,
        "ceferino.zip": 104,
        "celeste.zip": 7511,
        "chargekid.zip": 1417,
        "chasm.zip": 9816,
        "chessisstupid.zip": 2989,
        "chip.zip": 1769,
        "chipndale.zip": 6155,
        "chromavescence.zip": 199,
        "cityglitch.zip": 283,
        "clannad.zip": 927,
        "classicube.zip": 6195,
        "cleavingcaliber.zip": 666,
        "cliff_hanger.zip": 2585,
        "climb.zip": 554,
        "clockwind.zip": 1733,
        "cmdungeon.zip": 77,
        "cognizance.zip": 73,
        "colorlines.zip": 783,
        "commander.genius.zip": 8300,
        "cookservedelicious.zip": 206,
        "corsixth.zip": 7798,
        "cosmiccleaning.zip": 151,
        "cosmo-engine.zip": 1955,
        "cosmosmash.zip": 145,
        "cromagrally.zip": 5520,
        "cropsmare.zip": 338,
        "crysalis.zip": 631,
        "crystalsamalgam.zip": 921,
        "curseball.zip": 1153,
        "curseofthearrow.zip": 3045,
        "cybarian.zip": 1678,
        "daikatana.zip": 2320,
        "darksheep.zip": 100,
        "davegnukem.zip": 2197,
        "daydreamer.zip": 210,
        "deadicedeluxe.zip": 2417,
        "deathchase3d.zip": 116,
        "deep_sleep.zip": 1585,
        "defshot.zip": 765,
        "deltarune.zip": 465,
        "demodome.zip": 163,
        "demonizer.zip": 693,
        "demonkeep.zip": 631,
        "demonofsakurapass.zip": 171,
        "demonstone64.zip": 211,
        "depthsoflimbo.zip": 838,
        "derclou.zip": 2606,
        "derelict.zip": 121,
        "descent.zip": 6553,
        "descent2.zip": 4971,
        "descent3.zip": 1097,
        "destructivator.zip": 230,
        "destructivator2.zip": 167,
        "devbootleg.zip": 636,
        "devilutionx.zip": 27164,
        "dfencervstheorb.zip": 217,
        "dinothawr.zip": 3854,
        "diverdown.zip": 2087,
        "domeromantik.zip": 8120,
        "donut.dodo.zip": 1541,
        "doom2d.zip": 478,
        "doom2rpg.zip": 362,
        "doom3.zip": 14760,
        "doomrpg.zip": 930,
        "downwell.zip": 2137,
        "drally.zip": 2354,
        "drbloodshot.zip": 534,
        "drilbertiidiggeredoo.zip": 146,
        "drinkndrive.zip": 258,
        "droid7.zip": 695,
        "duke.nukem.3d.zip": 17566,
        "duke3dawo.zip": 3509,
        "dungeoncrawlstonesoup.zip": 596,
        "dungeonrush.zip": 2141,
        "dungeonsouls.zip": 3811,
        "dynamate_playdate.zip": 464,
        "echo_chamber.zip": 9515,
        "edna.zip": 634,
        "eity.zip": 3450,
        "elecdude.zip": 82,
        "elechead.zip": 302,
        "emojimerge.zip": 1926,
        "endlessdungeon.zip": 693,
        "enigma.zip": 1549,
        "entwined.zip": 115,
        "escape.zip": 1000,
        "everpatch.zip": 1074,
        "exhumed.zip": 3769,
        "exult.zip": 2450,
        "ez.zip": 482,
        "f-zeropocket.zip": 3645,
        "f1race.zip": 2635,
        "f1spirit.zip": 3111,
        "fade_to_black.zip": 2059,
        "faithdemonsiege.zip": 266,
        "fallenleaf.zip": 240,
        "falling_time.zip": 1457,
        "fallout.1.zip": 6,
        "fallout1.zip": 18185,
        "fallout2.zip": 16189,
        "farmner.zip": 3265,
        "feather.park.zip": 3806,
        "fheroes2.zip": 8629,
        "fightorperish.zip": 557,
        "final_quest.zip": 1768,
        "finding_paradise.zip": 1407,
        "fire_and_fondness2.zip": 904,
        "firearrow.zip": 985,
        "fistbump.zip": 118,
        "flare.zip": 5400,
        "flaskoman.zip": 98,
        "flywrench.zip": 181,
        "fnafnes.zip": 246,
        "forager.zip": 2228,
        "forgodden.zip": 1552,
        "formula_1_playdate.zip": 849,
        "foxtower.zip": 2237,
        "franken.zip": 356,
        "freedink.zip": 606,
        "freedom.planet.zip": 6279,
        "freedroid.zip": 4949,
        "freegemas.zip": 7444,
        "freegish.zip": 159,
        "freeserf.zip": 1345,
        "freesiege.zip": 412,
        "freesynd.zip": 1041,
        "frogfall.zip": 232,
        "frogger2.zip": 166,
        "frozen-bubble.zip": 2156,
        "fungusreaper.zip": 228,
        "galaxyforcesv2.zip": 560,
        "gameinfo.zip": 20616,
        "gardenstory.zip": 408,
        "gatoroboto.zip": 565,
        "gaugeofrage.zip": 142,
        "gaurodan.zip": 642,
        "gcrash.zip": 1253,
        "gemrb.zip": 3079,
        "geometrystrike.zip": 1146,
        "ghostris.zip": 38,
        "gigalomania.zip": 3772,
        "globeba.zip": 2168,
        "gmu.music.player.zip": 3164,
        "gnurobbo.zip": 946,
        "goblindungeoneer.zip": 59,
        "goinghomerevisited.zip": 1692,
        "goldenhornet.zip": 68,
        "goldminer.zip": 286,
        "grafx2.zip": 616,
        "gravitycircuit.zip": 4113,
        "grielsquest.zip": 61,
        "grimstorm.zip": 1491,
        "gta3.zip": 27934,
        "gtavc.zip": 34033,
        "guacamelee.zip": 470,
        "gumchugirl.zip": 569,
        "gumgem.zip": 969,
        "gumgirlgb.zip": 959,
        "gunsandguns.zip": 499,
        "hakopalace.zip": 188,
        "half-life.zip": 39035,
        "hallowe_en.zip": 38,
        "halloweenforever.zip": 64,
        "hallowseve.zip": 1231,
        "hatchwell.zip": 87,
        "hauntedlandsburial.zip": 113,
        "hawkisland.zip": 254,
        "hawkthorne.zip": 3154,
        "heart.of.darkness.zip": 4413,
        "hebihebi.zip": 286,
        "heboris-sdl.zip": 1621,
        "help.no.brake.zip": 6878,
        "heroes.zip": 231,
        "hex-a-hop.zip": 1962,
        "hexen2.zip": 4391,
        "hftsr.zip": 6323,
        "hijinx.zip": 1299,
        "hocoslamfy.zip": 2213,
        "holonomy.zip": 1500,
        "holotzcastle.zip": 167,
        "honeyguardian.zip": 190,
        "hordes.zip": 112,
        "hota.zip": 1311,
        "hotlinesanzu.zip": 852,
        "hoverboard.zip": 1658,
        "hovertank3d.zip": 160,
        "humming.out.zip": 415,
        "hunters.zip": 1945,
        "hurrican.zip": 3637,
        "hydorah.zip": 2121,
        "hydra.castle.labyrinth.zip": 6033,
        "hyper.jump.zip": 767,
        "hyperfight.zip": 2397,
        "hyperprincesspitch.zip": 241,
        "iconoclasts.zip": 9339,
        "icytower.zip": 1168,
        "iichantra_pear.zip": 4015,
        "iii.zip": 91,
        "images.000.zip": 94185,
        "images.001.zip": 62562,
        "images.002.zip": 62144,
        "images.003.zip": 67437,
        "images.004.zip": 97084,
        "images.005.zip": 109424,
        "images.006.zip": 7008,
        "images.007.zip": 6,
        "images.zip": 279483,
        "inertiablast.zip": 766,
        "infra_arcana.zip": 1247,
        "invaders.zip": 2673,
        "ioawn4t.zip": 1954,
        "ionfury.zip": 393,
        "iortcw.zip": 12606,
        "iosas.zip": 402,
        "ironferret.zip": 842,
        "itcamefromtheforest.zip": 364,
        "jazz2.zip": 3547,
        "jediacademy.zip": 8073,
        "jedioutcast.zip": 7454,
        "jestershelper.zip": 338,
        "jetlancer.zip": 256,
        "jetsetwilly.zip": 1398,
        "jugglrx.zip": 156,
        "jumpnbump.zip": 1137,
        "jumpoffthebridge.zip": 181,
        "jumponhead.zip": 23,
        "justanotherpong.zip": 1406,
        "kaijubigbattel.zip": 142,
        "kaima.zip": 212,
        "kanon.zip": 348,
        "kemonorogue.zip": 1343,
        "kenslabyrinth.zip": 1822,
        "kikai.zip": 357,
        "kingofmachines.zip": 3182,
        "klorets.zip": 515,
        "kobodeluxe.zip": 992,
        "kuklomenos.zip": 211,
        "labremnants.zip": 252,
        "labyrinthoflegendaryloot.zip": 1693,
        "laserkombat.zip": 860,
        "lastmission.zip": 154,
        "lawnbusterforhire.zip": 134,
        "lbreakouthd.zip": 6950,
        "legbreaker.zip": 307,
        "librespot.zip": 2061,
        "lierolibre.zip": 1487,
        "liltanks.zip": 187,
        "lineoff.zip": 296,
        "lisathebashful.zip": 336,
        "lisathehopeful.zip": 567,
        "lisathejoyful.zip": 1205,
        "lisathepainful.zip": 1794,
        "lisathepointless.zip": 453,
        "lisathetimeless.zip": 324,
        "lisatheunbreakable.zip": 433,
        "lisatheundone.zip": 348,
        "littlebusters.zip": 313,
        "littlefroggame.zip": 586,
        "littlegptracker.zip": 594,
        "littlerunmo.zip": 4299,
        "lividmeadow.zip": 688,
        "locust.zip": 261,
        "lode.zip": 928,
        "loderunneronline.zip": 2070,
        "loopcat.zip": 531,
        "lose95.zip": 167,
        "lostethereal.zip": 38,
        "love.zip": 433,
        "love3.zip": 363,
        "luck.be.a.landlord.zip": 1534,
        "luminousslash.zip": 278,
        "mableandthewood.zip": 902,
        "magicalbroom.zip": 182,
        "magicvigilante.zip": 529,
        "magnibox.zip": 288,
        "mago.zip": 516,
        "maldita.castilla.zip": 15816,
        "manicminer.zip": 1616,
        "margot_beatrice_adventure.zip": 2524,
        "maxdownforce.zip": 2828,
        "maximilien_adventure.zip": 4161,
        "meandmyshadow.zip": 1815,
        "megaman.zip": 6926,
        "megamanx816-bit.zip": 2566,
        "meritous.zip": 2163,
        "metanethunterg4.zip": 349,
        "mightymike.zip": 903,
        "mimisdeliverydash.zip": 1072,
        "minesector.zip": 3642,
        "minetest.zip": 10861,
        "minidoom.zip": 955,
        "minidoom2.zip": 746,
        "minit.zip": 1882,
        "mire.zip": 1394,
        "mirrormagic.zip": 1161,
        "missdriller.zip": 2782,
        "missiledancer.zip": 328,
        "mobility.zip": 234,
        "mojotron.zip": 497,
        "moonlight.zip": 15666,
        "moonlightnew.zip": 9945,
        "mr.boom.zip": 5728,
        "mreader.zip": 2005,
        "mrrescue.zip": 2835,
        "mslugsbf.zip": 1217,
        "multimanicminer.zip": 398,
        "multris.zip": 2099,
        "murtop.zip": 514,
        "mutant_tank_knights.zip": 631,
        "mystikbelle.zip": 1004,
        "mythos.zip": 2303,
        "nainainights.zip": 519,
        "nam.zip": 2485,
        "nanobounce.zip": 633,
        "nanosaur.zip": 956,
        "nanosaur2.zip": 2378,
        "nebulus.zip": 2044,
        "neogensokyo.zip": 1532,
        "neoncityriders.zip": 907,
        "ner.zip": 475,
        "netsurf.zip": 4148,
        "neverball.zip": 5874,
        "nextdoor.zip": 95,
        "nfs2se.zip": 5701,
        "nidhogg.zip": 1186,
        "nightshift.zip": 100,
        "nikwi.zip": 168,
        "njam.zip": 21,
        "nkaruga.zip": 5526,
        "nonny.zip": 4397,
        "nonstopspaceprobe.zip": 109,
        "noparachute.zip": 536,
        "nothing.zip": 846,
        "notransmission.zip": 703,
        "nova_pinball.zip": 3476,
        "npuzzle.zip": 983,
        "nuclearthronemobile.zip": 6124,
        "nulldrifter.zip": 331,
        "nuvie.zip": 106,
        "nvpw.zip": 643,
        "ocda.zip": 214,
        "oceansheart.zip": 3632,
        "oddworld.zip": 4529,
        "ohmygodlookatthisknight.zip": 9,
        "omegastrike.zip": 1456,
        "openblok.zip": 4513,
        "openclaw.zip": 6204,
        "openfodder.zip": 3081,
        "openggs.zip": 2793,
        "openjazz.zip": 8429,
        "openmrac.zip": 4204,
        "openomf.zip": 3975,
        "openrct2.zip": 3590,
        "opensupaplex.zip": 1358,
        "opensyobon.zip": 3355,
        "openttd.zip": 1761,
        "opentyrian.zip": 9272,
        "opentyrian2000.zip": 303,
        "openxcom.zip": 3188,
        "operationsteel.zip": 120,
        "operius.zip": 875,
        "oquonie.zip": 968,
        "osanasrevenge.zip": 1013,
        "ottomatic.zip": 1992,
        "outlawn.zip": 79,
        "outofammo.zip": 3186,
        "overgun.zip": 895,
        "owlboy.zip": 12496,
        "pachi.zip": 104,
        "pacman.zip": 10168,
        "panicroom.zip": 221,
        "panzerpaladin.zip": 3905,
        "passage.zip": 195,
        "paused.zip": 1712,
        "pekka-kana-2.zip": 1603,
        "penguincommand.zip": 157,
        "pigeon.zip": 2375,
        "pinball_disc_room.zip": 1070,
        "pingo.zip": 480,
        "pingus.zip": 82,
        "pixelheat.zip": 2737,
        "plague.zip": 500,
        "planetarian.zip": 381,
        "planetd4rk.zip": 116,
        "planetwaves.zip": 1463,
        "plaqueattackremake.zip": 665,
        "plumberssdl.zip": 572,
        "pocketcrystalleague.zip": 2830,
        "pockettactics.zip": 4143,
        "pocketwondersport.zip": 1456,
        "portmaster.zip": 62554,
        "postvoid.zip": 1319,
        "powder.zip": 3727,
        "powerlevel.zip": 847,
        "powerputtlegend.zip": 451,
        "ppengui.zip": 221,
        "prehistorik.2.zip": 4545,
        "profadeluxe.zip": 3422,
        "prototype.zip": 4586,
        "psebay.zip": 3371,
        "psrl.zip": 493,
        "pullywog.zip": 313,
        "pulstario.zip": 216,
        "pupaipospacedx.zip": 163,
        "puremetal.zip": 348,
        "putridshotultra.zip": 230,
        "puztrix_playdate.zip": 371,
        "pyk.zip": 201,
        "quadrupleback.zip": 94,
        "quake.2.zip": 11678,
        "quake.zip": 24962,
        "quake3.zip": 11167,
        "quakespasm.zip": 2882,
        "ragingblasters.zip": 216,
        "rakuen.zip": 2241,
        "rambleplanet.zip": 36,
        "randungeon.zip": 231,
        "raptor.zip": 6176,
        "rawgl.zip": 8281,
        "reborn.zip": 1321,
        "rebound.zip": 403,
        "redhandsomehood.zip": 796,
        "redneck.rampage.rides.again.zip": 3642,
        "redneck.rampage.zip": 4483,
        "redo.zip": 416,
        "redtrees.zip": 660,
        "redtrianglesc.zip": 21,
        "rejuvenation.zip": 1039,
        "relichunters.zip": 643,
        "reminiscence.zip": 3440,
        "render96ex.zip": 11397,
        "restore.portmaster.zip": 1500,
        "retrotime.zip": 1584,
        "revbros.zip": 271,
        "ri_li.zip": 2670,
        "rick.dangerous.zip": 8317,
        "rigelengine.zip": 2172,
        "riptale.zip": 282,
        "riskofrain.zip": 2346,
        "rite.zip": 490,
        "rlone.zip": 661,
        "rlvm.zip": 1394,
        "road.invaders.zip": 1310,
        "roadwarriors2.zip": 38,
        "rockdodger.zip": 171,
        "rocksndiamonds.zip": 2972,
        "roguelight.zip": 1996,
        "roswyn.zip": 67,
        "rota.zip": 11021,
        "rotationalshift.zip": 410,
        "rott.zip": 7333,
        "rrootage.zip": 264,
        "runtimes.zip": 1,
        "russiansubwaydogs.zip": 788,
        "rvgl.zip": 18992,
        "rwatch.zip": 255,
        "satlovecake.zip": 86,
        "satryn.zip": 1805,
        "savant.zip": 1331,
        "savingprincess.zip": 73,
        "scaletheskulltower.zip": 313,
        "sdlbomber.zip": 206,
        "sdlpal.zip": 463,
        "sdlpop.zip": 10322,
        "sdlsopwith.zip": 1182,
        "secretteagarden.zip": 130,
        "septuple.zip": 89,
        "serioussam-tfe.zip": 5370,
        "serioussam-tse.zip": 5099,
        "sevenkingdoms.zip": 1836,
        "shadow.warrior.zip": 5041,
        "shippy.zip": 526,
        "shipwreck.zip": 1897,
        "shirobimetal.zip": 103,
        "shovel.knight.zip": 30031,
        "shrubnaut.zip": 349,
        "siegeofosaka.zip": 1490,
        "simonsqrev.zip": 7578,
        "simplesokoban.zip": 3786,
        "skeletonboomerang.zip": 67,
        "skifree.zip": 3831,
        "skijump3.zip": 4710,
        "sm.zip": 5299,
        "smoothiegalaxy.zip": 2666,
        "smw.zip": 33,
        "smworld.zip": 7592,
        "snaklipse.zip": 1259,
        "sneakr.zip": 223,
        "sneggpit.zip": 806,
        "snkrx.zip": 549,
        "snout.zip": 695,
        "soh.zip": 12932,
        "soh2.zip": 5652,
        "sokobrawn.zip": 483,
        "somnokid.zip": 166,
        "sonic.1.zip": 8572,
        "sonic.2.zip": 7270,
        "sonic.cd.zip": 7866,
        "sonic.mania.zip": 19015,
        "sonic1sms.zip": 3261,
        "sonic2sms.zip": 2551,
        "sonic3air.zip": 1570,
        "sonic3sms.zip": 2583,
        "sonictimetwisted.zip": 1225,
        "sonictt16b.zip": 2412,
        "sorr.zip": 11373,
        "space.cadet.pinball.zip": 13129,
        "spacegladiators.zip": 190,
        "spacemothdx.zip": 71,
        "spacewingwar.zip": 111,
        "spearmintmountain.zip": 358,
        "spectralslash.zip": 353,
        "spellsling.zip": 808,
        "spelltower.zip": 1735,
        "spelunky.zip": 20894,
        "spinch.zip": 302,
        "splinterzone.zip": 29,
        "spooky.zip": 722,
        "spookynakki.zip": 411,
        "squeek.zip": 188,
        "srb2.zip": 12075,
        "srb2kart.zip": 11144,
        "starboy.zip": 829,
        "starcatcher.zip": 4650,
        "stardewvalley.zip": 87326,
        "stargrovescramble.zip": 3958,
        "starvsthegame.zip": 610,
        "static.zip": 128,
        "steelassault.zip": 4941,
        "stop_the_eggspress.zip": 384,
        "stoptheeggspress.zip": 12,
        "strangeadventures.zip": 1748,
        "streetsofclaus.zip": 672,
        "strikeysisters.zip": 886,
        "sudokul.zip": 3038,
        "sulka.zip": 1059,
        "sunsetshaped.zip": 743,
        "sunsetwitchclassic.zip": 193,
        "super.mario.war.zip": 18441,
        "supercakeboy.zip": 558,
        "supercratebox.zip": 1631,
        "superdrome.bugs.zip": 336,
        "superdungeonmuncher.zip": 421,
        "supergaelicdodgeball.zip": 141,
        "supermeatboy.zip": 5613,
        "supermegazero.zip": 146,
        "supermethanebros.zip": 160,
        "superraftboatclassic.zip": 551,
        "superrobotninjagirl.zip": 873,
        "superskelemania.zip": 35,
        "superstarpath.zip": 531,
        "supertransball2.zip": 164,
        "supertux.zip": 6752,
        "supertuxkart.zip": 9213,
        "superxyx.zip": 771,
        "swapwoodquestr.zip": 1458,
        "tabletanks.zip": 60,
        "tailsadventure.zip": 2695,
        "tailspin.zip": 188,
        "tamatool.zip": 1560,
        "tamiku.zip": 34,
        "techmaniac.zip": 175,
        "templeofkashteki.zip": 344,
        "tempuslocus.zip": 129,
        "terminus.zip": 148,
        "thecurseofissyos.zip": 1419,
        "thelegendoflumina.zip": 1621,
        "thermomorph.zip": 1699,
        "thestarlitescape.zip": 734,
        "thesunandmoon.zip": 306,
        "thewind.zip": 36,
        "thextech.zip": 912,
        "threecoins.zip": 1226,
        "thwack.zip": 1770,
        "tileworld.zip": 2902,
        "timespinner.zip": 11580,
        "tiny-crate.zip": 4872,
        "tinystg.zip": 1252,
        "titan_tactics.zip": 4926,
        "tmntsr.zip": 36011,
        "to_the_moon.zip": 3952,
        "tomb.raider.1.zip": 10007,
        "tomoyo_after.zip": 443,
        "topnep.zip": 110,
        "towardsthepantheones.zip": 130,
        "towerbabe.zip": 73,
        "towerbag.zip": 292,
        "towerfall.zip": 2412,
        "towerfortress.zip": 422,
        "trickykeys.zip": 841,
        "trickykeys2.zip": 628,
        "triggerrally.zip": 683,
        "trogdorrb.zip": 975,
        "trolley.delayma.zip": 340,
        "tsunderswap.zip": 37,
        "tube64.zip": 2823,
        "tumbledown.zip": 90,
        "tunics.zip": 1588,
        "turbotabletennis.zip": 1394,
        "tuxfootball.zip": 95,
        "tuxpuck.zip": 228,
        "tvruhh.zip": 143,
        "twodie.zip": 186,
        "ubermoshcollection.zip": 594,
        "udlrmodify.zip": 645,
        "ufo50.zip": 4459,
        "ultimatestunts.zip": 3229,
        "ultimatetapankaikki.zip": 1626,
        "undertale.zip": 24214,
        "ungratefulbirdsngd.zip": 6,
        "unlikely.zip": 292,
        "upo.zip": 1325,
        "uqm.zip": 4025,
        "utyellow.zip": 2252,
        "valhalla.zip": 3250,
        "vanillara.zip": 5375,
        "vanillatd.zip": 3790,
        "vcmi.zip": 6685,
        "vdrift.zip": 696,
        "verticaldropheroeshd.zip": 114,
        "vhr.zip": 297,
        "vikingsofmidgard.zip": 905,
        "viralreload.zip": 155,
        "vitasnake.zip": 338,
        "vodovod.zip": 156,
        "voidpyramid.zip": 68,
        "voidstranger.zip": 586,
        "vvvvvv.zip": 13488,
        "wakingmars.zip": 571,
        "walthrosrenewal.zip": 55,
        "waternet.zip": 1318,
        "wetspot2.zip": 979,
        "widelands.zip": 3211,
        "wipeout.zip": 5469,
        "wizardchase.zip": 1765,
        "wizardorb.zip": 382,
        "wizznic.zip": 747,
        "wolf3d.zip": 2463,
        "wordlesdl.zip": 3013,
        "wordswithfreds.zip": 1002,
        "world.war.ii.gi.zip": 3288,
        "worldofgoo.zip": 3377,
        "worship_vector.zip": 1567,
        "xenonvalkyrie.zip": 1708,
        "xooxenoxafari.zip": 44,
        "yarntown.zip": 1544,
        "yarsrevenge.zip": 44,
        "yatka.zip": 6724,
        "yellowjacket.zip": 382,
        "yolkheroes.zip": 235,
        "youdiedbanry.zip": 266,
        "youhave10s2023.zip": 366,
        "z-warp.zip": 229,
        "zelda-bookofmudora.zip": 2267,
        "zelda-mercurischest.zip": 1028,
        "zelda-mysteryofsolarusdx.zip": 2363,
        "zelda-mysteryofsolarusxd.zip": 1509,
        "zelda-roth-se.zip": 1867,
        "zelda3.zip": 5551,
        "zelda3t.zip": 770,
        "zelda_roth.zip": 779,
        "zeldansq.zip": 764,
        "zeldaolb.zip": 10431,
        "zeldaxd-mercurischess.zip": 1961,
        "zeldoschallenge.zip": 1507,
        "zeldoschallenge2.zip": 1843,
        "zeroptianinvasion.zip": 55,
        "zeroranger.zip": 1966,
        "zgloom.zip": 4234,
        "ziggurat.zip": 625,
        "ziiaol.zip": 1430,
        "znax.zip": 2138
    },
    "total_downloads": 2194331
}